{"status":"done","chunks":{"laboratorio":[{"name":"laboratorio.js","path":"/Users/fabioandresgarciasanchez/PycharmProjects/laboratorio/static/assets/bundles/deve/laboratorio.js"}]},"error":"ModuleBuildError","message":"Module build failed: SyntaxError: Unexpected token (86:56)\n\n  84 | \n  85 |     renderVerificar() {\n> 86 |         const {orden_examen: {mis_firmas}, orden_examen:} = this.props;\n     |                                                         ^\n  87 |         if (mis_firmas.length > 0) {\n  88 |             return (\n  89 |                 <div>cosa</div>\n"}